kitty/__init__.py
kitty/bin/__init__.py
kitty/bin/kitty_template_tester.py
kitty/bin/kitty_tool.py
kitty/bin/kitty_web_client.py
kitty/controllers/__init__.py
kitty/controllers/base.py
kitty/controllers/client.py
kitty/controllers/empty.py
kitty/core/__init__.py
kitty/core/actor.py
kitty/core/kassert.py
kitty/core/kitty_object.py
kitty/core/threading_utils.py
kitty/data/__init__.py
kitty/data/data_manager.py
kitty/data/report.py
kitty/fuzzers/__init__.py
kitty/fuzzers/base.py
kitty/fuzzers/client.py
kitty/fuzzers/server.py
kitty/fuzzers/test_list.py
kitty/interfaces/__init__.py
kitty/interfaces/base.py
kitty/interfaces/web.py
kitty/interfaces/web/static/bootstrap.min.css
kitty/interfaces/web/static/bootstrap.min.js
kitty/interfaces/web/static/cytoscape.min.js
kitty/interfaces/web/static/favicon.ico
kitty/interfaces/web/static/filesaver.min.js
kitty/interfaces/web/static/hexdump.js
kitty/interfaces/web/static/index.html
kitty/interfaces/web/static/jquery-1.11.1.js
kitty/interfaces/web/static/jquery.js
kitty/interfaces/web/static/jszip.min.js
kitty/interfaces/web/static/report.html
kitty/interfaces/web/static/style.css
kitty/model/__init__.py
kitty/model/high_level/__init__.py
kitty/model/high_level/base.py
kitty/model/high_level/graph.py
kitty/model/high_level/random_sequence.py
kitty/model/high_level/staged_sequence.py
kitty/model/low_level/__init__.py
kitty/model/low_level/aliases.py
kitty/model/low_level/calculated.py
kitty/model/low_level/condition.py
kitty/model/low_level/container.py
kitty/model/low_level/container_mutator.py
kitty/model/low_level/encoder.py
kitty/model/low_level/field.py
kitty/model/low_level/ll_utils.py
kitty/model/low_level/mutated_field.py
kitty/monitors/__init__.py
kitty/monitors/base.py
kitty/remote/__init__.py
kitty/remote/actor.py
kitty/remote/rpc.py
kitty/targets/__init__.py
kitty/targets/base.py
kitty/targets/client.py
kitty/targets/empty.py
kitty/targets/server.py
kittyfuzzer-0.7.4.dist-info/COPYING
kittyfuzzer-0.7.4.dist-info/METADATA
kittyfuzzer-0.7.4.dist-info/WHEEL
kittyfuzzer-0.7.4.dist-info/entry_points.txt
kittyfuzzer-0.7.4.dist-info/top_level.txt
kittyfuzzer-0.7.4.dist-info/RECORD
