Metadata-Version: 2.1
Name: kittyfuzzer
Version: 0.7.4
Summary: Kitty fuzzing framework
Home-page: https://github.com/cisco-sas/kitty.git
Author: Cisco SAS team
Author-email: kitty-fuzzer@googlegroups.com
License: UNKNOWN
Keywords: fuzz,fuzzing,framework,sulley,kitty,kittyfuzzer,security
Platform: UNKNOWN
Requires-Dist: docopt
Requires-Dist: bitstring
Requires-Dist: six
Requires-Dist: requests
